globalmart_api/__init__.py
globalmart_api/oops.py
test_globalmart_api-0.2.dist-info/License.txt
test_globalmart_api-0.2.dist-info/METADATA
test_globalmart_api-0.2.dist-info/WHEEL
test_globalmart_api-0.2.dist-info/top_level.txt
test_globalmart_api-0.2.dist-info/RECORD
