Metadata-Version: 2.1
Name: test-globalmart-api
Version: 0.2
Summary: API package that provides us the method to fetch the data from the API, along with the method to convert that into proper dataframe
Author: Burhan
Author-email: burhanuddinnahargarwala@gmail.com
License: MIT
License-File: License.txt
Requires-Dist: pandas
Requires-Dist: requests
